Metadata-Version: 2.4
Name: slicesight-next-mang
Version: 0.2.0
Summary: Advanced Redis hotspot detection and analysis
Project-URL: Homepage, https://github.com/slicesight/slicesight-next
Project-URL: Documentation, https://slicesight-next.readthedocs.io/
Project-URL: Repository, https://github.com/slicesight/slicesight-next.git
Project-URL: Issues, https://github.com/slicesight/slicesight-next/issues
Author-email: SliceSight Team <team@slicesight.dev>
License: MIT
License-File: LICENSE
Keywords: cluster,distributed-systems,hotspot,monitoring,performance,redis
Classifier: Development Status :: 4 - Beta
Classifier: Intended Audience :: Developers
Classifier: Intended Audience :: System Administrators
Classifier: License :: OSI Approved :: MIT License
Classifier: Operating System :: OS Independent
Classifier: Programming Language :: Python :: 3
Classifier: Programming Language :: Python :: 3.10
Classifier: Programming Language :: Python :: 3.11
Classifier: Programming Language :: Python :: 3.12
Classifier: Topic :: Database
Classifier: Topic :: System :: Distributed Computing
Classifier: Topic :: System :: Monitoring
Requires-Python: >=3.10
Requires-Dist: rich>=13.0.0
Requires-Dist: typer[all]>=0.9.0
Provides-Extra: dev
Requires-Dist: mypy>=1.0.0; extra == 'dev'
Requires-Dist: pre-commit>=3.0.0; extra == 'dev'
Requires-Dist: ruff>=0.1.0; extra == 'dev'
Provides-Extra: test
Requires-Dist: hypothesis>=6.0.0; extra == 'test'
Requires-Dist: pytest-benchmark>=4.0.0; extra == 'test'
Requires-Dist: pytest-cov>=4.0.0; extra == 'test'
Requires-Dist: pytest>=7.0.0; extra == 'test'
Requires-Dist: testcontainers>=3.0.0; extra == 'test'
